keyosk/__about__.py
keyosk/__init__.py
keyosk/__main__.py
keyosk/py.typed
keyosk-0.1.0a0.dist-info/LICENSE.md
keyosk-0.1.0a0.dist-info/WHEEL
keyosk-0.1.0a0.dist-info/METADATA
keyosk-0.1.0a0.dist-info/RECORD
